{
    "type":        "minecraft:crafting_shapeless",
    "ingredients": [
        {
            "item": "minecraft:emerald"
        },
        {
            "item": "minecraft:emerald"
        },
        {
            "item": "minecraft:emerald"
        },
        {
            "item": "minecraft:emerald"
        },
        {
            "item": "minecraft:stone"
        },
        {
            "item": "minecraft:stone"
        },
        {
            "item": "minecraft:stone"
        },
        {
            "item": "minecraft:stone"
        },
        {
            "item": "minecraft:stone"
        }
    ],
    "result":      {
        "item":  "minecraft:emerald_ore",
        "count": 1
    }
}
